wowint/__init__.py
wowint-2025.2.3448.dist-info/METADATA
wowint-2025.2.3448.dist-info/WHEEL
wowint-2025.2.3448.dist-info/licenses/LICENSE
wowint-2025.2.3448.dist-info/RECORD
