Metadata-Version: 2.4
Name: wowint
Version: 2025.2.3448
Summary: Mapping of Scratch to Warcraft (keyboard and Xbox) using iid42
Project-URL: Homepage, https://github.com/EloiStree/pypi_wowint
Project-URL: Issues, https://github.com/EloiStree/pypi_wowint
Author-email: Eloi Stree <eloistree@gmail.com>
License-File: LICENSE
Keywords: IID,date,development,game,index,integer
Classifier: Development Status :: 1 - Planning
Classifier: Operating System :: OS Independent
Classifier: Programming Language :: Python :: 3
Requires-Python: >=3.0
Requires-Dist: iid42
